debian_interfaces_parser
